sizhi/__init__.py
sizhi/sizhi.py
sizhi-4.1.dist-info/LICENSE
sizhi-4.1.dist-info/METADATA
sizhi-4.1.dist-info/WHEEL
sizhi-4.1.dist-info/top_level.txt
sizhi-4.1.dist-info/RECORD
