Metadata-Version: 2.1
Name: sizhi
Version: 4.1
Summary: 中国行政区划四至点位获取、区划shp、geojson下载及流式裁剪链接
Home-page: https://space.bilibili.com/31106656
Author: pianshilengyubing
Author-email: 1010221702@qq.com
Classifier: Programming Language :: Python :: 3
Classifier: License :: OSI Approved :: MIT License
Classifier: Operating System :: OS Independent
License-File: LICENSE
